skystar/__init__.py
skystar/core.py
skystar/cuda.py
skystar/dataloader.py
skystar/dataset.py
skystar/graph.py
skystar/layer.py
skystar/model.py
skystar/optimizer.py
skystar/transforms.py
skystar/utils.py
skystar/voc2012.py
skystar/sky_dataset/__init__.py
skystar/sky_dataset/create_dataset.py
skystar/sky_dataset/load.py
skystar-1.0.55.dist-info/LICENSE.txt
skystar-1.0.55.dist-info/METADATA
skystar-1.0.55.dist-info/WHEEL
skystar-1.0.55.dist-info/entry_points.txt
skystar-1.0.55.dist-info/top_level.txt
skystar-1.0.55.dist-info/RECORD
