Metadata-Version: 2.1
Name: skystar
Version: 1.0.55
Summary: A Deep Learning Framework For Beginners
Home-page: https://github.com/Yonas-Xin/STARSKY
Author: Yonas-xin
Author-email: linkstar443@163.com
Classifier: Programming Language :: Python :: 3
Classifier: License :: OSI Approved :: MIT License
Classifier: Operating System :: OS Independent
Requires-Python: >=3.10
License-File: LICENSE.txt
Requires-Dist: colorama ==0.4.6
Requires-Dist: markdown-it-py ==3.0.0
Requires-Dist: mdurl ==0.1.2
Requires-Dist: numpy ==2.1.3
Requires-Dist: onnx ==1.17.0
Requires-Dist: onnxsim ==0.4.36
Requires-Dist: pillow ==11.0.0
Requires-Dist: protobuf ==5.29.0
Requires-Dist: Pygments ==2.18.0
Requires-Dist: rich ==13.9.4
Requires-Dist: tqdm ==4.67.1
Requires-Dist: typing-extensions ==4.12.2
